source_google_analytics_data_api/__init__.py
source_google_analytics_data_api/components.py
source_google_analytics_data_api/manifest.yaml
source_google_analytics_data_api/run.py
source_google_analytics_data_api/source.py
airbyte_source_google_analytics_data_api-2.8.2.dist-info/METADATA
airbyte_source_google_analytics_data_api-2.8.2.dist-info/WHEEL
airbyte_source_google_analytics_data_api-2.8.2.dist-info/entry_points.txt
airbyte_source_google_analytics_data_api-2.8.2.dist-info/RECORD
